LICENSE
pyridy/__init__.py
pyridy/campaign.py
pyridy/config.py
pyridy/file.py
pyridy/osm/__init__.py
pyridy/osm/osm.py
pyridy/osm/utils/__init__.py
pyridy/osm/utils/elements.py
pyridy/osm/utils/overpass.py
pyridy/osm/utils/query.py
pyridy/osm/utils/relation.py
pyridy/osm/utils/tools.py
pyridy/processing/__init__.py
pyridy/processing/comfort.py
pyridy/processing/condition.py
pyridy/processing/excitation.py
pyridy/processing/processor.py
pyridy/utils/__init__.py
pyridy/utils/device.py
pyridy/utils/sensor.py
pyridy/utils/timeseries.py
pyridy/utils/tools.py
pyridy/widgets/__init__.py
pyridy/widgets/map.py
pyridy-1.0.5.dist-info/LICENSE
pyridy-1.0.5.dist-info/METADATA
pyridy-1.0.5.dist-info/WHEEL
pyridy-1.0.5.dist-info/RECORD
