Metadata-Version: 2.1
Name: pyridy
Version: 1.0.5
Summary: Support library for measurements made with the Ridy Android App
License: Apache-2.0
Keywords: signal processing,ridy,android
Author: Philipp Simon Leibner
Author-email: philipp.leibner@ifs.rwth-aachen.de
Requires-Python: >=3.9,<3.13
Classifier: Intended Audience :: Science/Research
Classifier: License :: OSI Approved :: Apache Software License
Classifier: Programming Language :: Python :: 3
Classifier: Programming Language :: Python :: 3.9
Classifier: Programming Language :: Python :: 3.10
Classifier: Programming Language :: Python :: 3.11
Classifier: Programming Language :: Python :: 3.12
Classifier: Topic :: Scientific/Engineering :: Information Analysis
Requires-Dist: HeapDict (>=1.0.1)
Requires-Dist: Shapely (>=1.8.1)
Requires-Dist: geopy (>=2.1.0)
Requires-Dist: ipyleaflet (>=0.19.0)
Requires-Dist: matplotlib (>=3.8.1)
Requires-Dist: networkx (>=3.1)
Requires-Dist: numpy (>=1.26.4)
Requires-Dist: overpy (>=0.6)
Requires-Dist: pandas (>=2.2.0)
Requires-Dist: pyproj (>=3.3.0)
Requires-Dist: pytest (>=8.1.1)
Requires-Dist: requests (>=2.28.1)
Requires-Dist: requests-cache (>=1.0.1)
Requires-Dist: rwthcolors (>=0.2.3)
Requires-Dist: scipy (>=1.6.3)
Requires-Dist: tqdm (>=4.60.0)
